piezense/__init__.py
piezense/piezense.py
piezense-0.0.3.dist-info/METADATA
piezense-0.0.3.dist-info/WHEEL
piezense-0.0.3.dist-info/top_level.txt
piezense-0.0.3.dist-info/RECORD
