Metadata-Version: 2.1
Name: piezense
Version: 0.0.3
Summary: A Python package for interfacing with PieZense pneumatic systems
Home-page: https://github.com/haptica-robotics/piezense
Author: Haptica Robotics
Author-email: info@hapticarobotics.com
License: LicenseRef-Proprietary
Platform: UNKNOWN
Requires-Python: >=3.8
Requires-Dist: bleak (==1.1.1)
